filterkaapi-0.1.4.dist-info/licenses/LICENSE
kaapi_lang/__init__.py
kaapi_lang/cli.py
kaapi_lang/context.py
kaapi_lang/functions.py
kaapi_lang/interpreter.py
kaapi_lang/lexer.py
kaapi_lang/main.py
kaapi_lang/parser.py
filterkaapi-0.1.4.dist-info/METADATA
filterkaapi-0.1.4.dist-info/WHEEL
filterkaapi-0.1.4.dist-info/entry_points.txt
filterkaapi-0.1.4.dist-info/top_level.txt
filterkaapi-0.1.4.dist-info/RECORD
