Metadata-Version: 2.4
Name: filterKaapi
Version: 0.1.4
Summary: FilterKaapi: A Tamil-inspired programming language
Author: Chiddesh
License: MIT
Requires-Python: >=3.7
License-File: LICENSE
Dynamic: author
Dynamic: description
Dynamic: description-content-type
Dynamic: license
Dynamic: license-file
Dynamic: requires-python
Dynamic: summary
